{".class": "MypyFile", "_fullname": "pybrat.parser", "is_partial_stub_package": false, "is_stub": false, "names": {".class": "SymbolTable", "BratParser": {".class": "SymbolTableNode", "kind": "Gdef", "node": {".class": "TypeInfo", "_promote": null, "abstract_attributes": [], "bases": ["builtins.object"], "declared_metaclass": null, "defn": {".class": "ClassDef", "fullname": "pybrat.parser.BratParser", "name": "BratParser", "type_vars": []}, "flags": [], "fullname": "pybrat.parser.BratParser", "metaclass_type": null, "metadata": {}, "module_name": "pybrat.parser", "mro": ["pybrat.parser.BratParser", "builtins.object"], "names": {".class": "SymbolTable", "__init__": {".class": "SymbolTableNode", "kind": "Mdef", "node": {".class": "FuncDef", "arg_kinds": [0, 1, 1], "arg_names": ["self", "ignore_types", "error"], "flags": [], "fullname": "pybrat.parser.BratParser.__init__", "name": "__init__", "type": {".class": "CallableType", "arg_kinds": [0, 1, 1], "arg_names": ["self", "ignore_types", "error"], "arg_types": ["pybrat.parser.BratParser", {".class": "UnionType", "items": [{".class": "Instance", "args": ["builtins.str"], "type_ref": "typing.Iterable"}, {".class": "NoneType"}]}, "builtins.str"], "bound_args": [], "def_extras": {"first_arg": "self"}, "fallback": "builtins.function", "implicit": false, "is_ellipsis_args": false, "name": "__init__ of BratParser", "ret_type": {".class": "NoneType"}, "variables": []}}}, "_check_entities": {".class": "SymbolTableNode", "kind": "Mdef", "node": {".class": "FuncDef", "arg_kinds": [0, 0], "arg_names": ["self", "entities"], "flags": [], "fullname": "pybrat.parser.BratParser._check_entities", "name": "_check_entities", "type": null}}, "_format_entities": {".class": "SymbolTableNode", "kind": "Mdef", "node": {".class": "FuncDef", "arg_kinds": [0, 0, 0], "arg_names": ["self", "entity_matches", "references"], "flags": [], "fullname": "pybrat.parser.BratParser._format_entities", "name": "_format_entities", "type": null}}, "_format_events": {".class": "SymbolTableNode", "kind": "Mdef", "node": {".class": "FuncDef", "arg_kinds": [0, 0, 0], "arg_names": ["self", "event_matches", "entities"], "flags": [], "fullname": "pybrat.parser.BratParser._format_events", "name": "_format_events", "type": null}}, "_format_relations": {".class": "SymbolTableNode", "kind": "Mdef", "node": {".class": "FuncDef", "arg_kinds": [0, 0, 0], "arg_names": ["self", "relation_matches", "entities"], "flags": [], "fullname": "pybrat.parser.BratParser._format_relations", "name": "_format_relations", "type": null}}, "_parse_ann": {".class": "SymbolTableNode", "kind": "Mdef", "node": {".class": "FuncDef", "arg_kinds": [0, 0], "arg_names": ["self", "ann"], "flags": [], "fullname": "pybrat.parser.BratParser._parse_ann", "name": "_parse_ann", "type": null}}, "_parse_entity": {".class": "SymbolTableNode", "kind": "Mdef", "node": {".class": "FuncDef", "arg_kinds": [0, 0], "arg_names": ["self", "line"], "flags": [], "fullname": "pybrat.parser.BratParser._parse_entity", "name": "_parse_entity", "type": null}}, "_parse_equivalence_relations": {".class": "SymbolTableNode", "kind": "Mdef", "node": {".class": "FuncDef", "arg_kinds": [0, 0], "arg_names": ["self", "line"], "flags": [], "fullname": "pybrat.parser.BratParser._parse_equivalence_relations", "name": "_parse_equivalence_relations", "type": null}}, "_parse_event": {".class": "SymbolTableNode", "kind": "Mdef", "node": {".class": "FuncDef", "arg_kinds": [0, 0], "arg_names": ["self", "line"], "flags": [], "fullname": "pybrat.parser.BratParser._parse_event", "name": "_parse_event", "type": null}}, "_parse_reference": {".class": "SymbolTableNode", "kind": "Mdef", "node": {".class": "FuncDef", "arg_kinds": [0, 0], "arg_names": ["self", "line"], "flags": [], "fullname": "pybrat.parser.BratParser._parse_reference", "name": "_parse_reference", "type": null}}, "_parse_relation": {".class": "SymbolTableNode", "kind": "Mdef", "node": {".class": "FuncDef", "arg_kinds": [0, 0], "arg_names": ["self", "line"], "flags": [], "fullname": "pybrat.parser.BratParser._parse_relation", "name": "_parse_relation", "type": null}}, "_parse_text": {".class": "SymbolTableNode", "kind": "Mdef", "node": {".class": "FuncDef", "arg_kinds": [0, 0], "arg_names": ["self", "txt"], "flags": [], "fullname": "pybrat.parser.BratParser._parse_text", "name": "_parse_text", "type": null}}, "_raise": {".class": "SymbolTableNode", "kind": "Mdef", "node": {".class": "FuncDef", "arg_kinds": [0, 0], "arg_names": ["self", "error"], "flags": [], "fullname": "pybrat.parser.BratParser._raise", "name": "_raise", "type": null}}, "_raise_invalid_line_error": {".class": "SymbolTableNode", "kind": "Mdef", "node": {".class": "FuncDef", "arg_kinds": [0, 0], "arg_names": ["self", "line"], "flags": [], "fullname": "pybrat.parser.BratParser._raise_invalid_line_error", "name": "_raise_invalid_line_error", "type": null}}, "_should_ignore_line": {".class": "SymbolTableNode", "kind": "Mdef", "node": {".class": "FuncDef", "arg_kinds": [0, 0], "arg_names": ["self", "line"], "flags": [], "fullname": "pybrat.parser.BratParser._should_ignore_line", "name": "_should_ignore_line", "type": null}}, "error": {".class": "SymbolTableNode", "implicit": true, "kind": "Mdef", "node": {".class": "Var", "flags": [], "fullname": "pybrat.parser.BratParser.error", "name": "error", "type": "builtins.str"}}, "exts": {".class": "SymbolTableNode", "implicit": true, "kind": "Mdef", "node": {".class": "Var", "flags": [], "fullname": "pybrat.parser.BratParser.exts", "name": "exts", "type": {".class": "Instance", "args": ["builtins.str"], "type_ref": "builtins.set"}}}, "parse": {".class": "SymbolTableNode", "kind": "Mdef", "node": {".class": "FuncDef", "arg_kinds": [0, 0], "arg_names": ["self", "dirname"], "flags": [], "fullname": "pybrat.parser.BratParser.parse", "name": "parse", "type": {".class": "CallableType", "arg_kinds": [0, 0], "arg_names": ["self", "dirname"], "arg_types": ["pybrat.parser.BratParser", {".class": "UnionType", "items": ["builtins.str", "builtins.bytes", {".class": "Instance", "args": [{".class": "AnyType", "missing_import_name": null, "source_any": null, "type_of_any": 4}], "type_ref": "builtins._PathLike"}]}], "bound_args": [], "def_extras": {"first_arg": "self"}, "fallback": "builtins.function", "implicit": false, "is_ellipsis_args": false, "name": "parse of BratParser", "ret_type": {".class": "Instance", "args": ["pybrat.parser.Example"], "type_ref": "builtins.list"}, "variables": []}}}, "re_ignore_types": {".class": "SymbolTableNode", "implicit": true, "kind": "Mdef", "node": {".class": "Var", "flags": ["explicit_self_type", "is_ready"], "fullname": "pybrat.parser.BratParser.re_ignore_types", "name": "re_ignore_types", "type": {".class": "UnionType", "items": [{".class": "Instance", "args": [{".class": "AnyType", "missing_import_name": null, "source_any": null, "type_of_any": 4}], "type_ref": "typing.Pattern"}, {".class": "NoneType"}]}}}, "types": {".class": "SymbolTableNode", "implicit": true, "kind": "Mdef", "node": {".class": "Var", "flags": [], "fullname": "pybrat.parser.BratParser.types", "name": "types", "type": {".class": "Instance", "args": ["builtins.str"], "type_ref": "builtins.set"}}}}, "tuple_type": null, "type_vars": [], "typeddict_type": null}}, "Entity": {".class": "SymbolTableNode", "kind": "Gdef", "node": {".class": "TypeInfo", "_promote": null, "abstract_attributes": [], "bases": ["builtins.object"], "declared_metaclass": null, "defn": {".class": "ClassDef", "fullname": "pybrat.parser.Entity", "name": "Entity", "type_vars": []}, "flags": [], "fullname": "pybrat.parser.Entity", "metaclass_type": null, "metadata": {"dataclass": {"attributes": [{"column": 4, "has_default": false, "is_in_init": true, "is_init_var": false, "line": 26, "name": "mention", "type": "builtins.str"}, {"column": 4, "has_default": false, "is_in_init": true, "is_init_var": false, "line": 27, "name": "type", "type": "builtins.str"}, {"column": 4, "has_default": false, "is_in_init": true, "is_init_var": false, "line": 28, "name": "start", "type": "builtins.int"}, {"column": 4, "has_default": false, "is_in_init": true, "is_init_var": false, "line": 29, "name": "end", "type": "builtins.int"}, {"column": 4, "has_default": true, "is_in_init": true, "is_init_var": false, "line": 30, "name": "references", "type": {".class": "Instance", "args": ["pybrat.parser.Reference"], "type_ref": "builtins.list"}}, {"column": 4, "has_default": true, "is_in_init": true, "is_init_var": false, "line": 31, "name": "id", "type": {".class": "UnionType", "items": ["builtins.str", {".class": "NoneType"}]}}], "frozen": false}}, "module_name": "pybrat.parser", "mro": ["pybrat.parser.Entity", "builtins.object"], "names": {".class": "SymbolTable", "__init__": {".class": "SymbolTableNode", "kind": "Mdef", "node": {".class": "FuncDef", "arg_kinds": [0, 0, 0, 0, 0, 1, 1], "arg_names": ["self", "mention", "type", "start", "end", "references", "id"], "flags": [], "fullname": "pybrat.parser.Entity.__init__", "name": "__init__", "type": {".class": "CallableType", "arg_kinds": [0, 0, 0, 0, 0, 1, 1], "arg_names": ["self", "mention", "type", "start", "end", "references", "id"], "arg_types": ["pybrat.parser.Entity", "builtins.str", "builtins.str", "builtins.int", "builtins.int", {".class": "Instance", "args": ["pybrat.parser.Reference"], "type_ref": "builtins.list"}, {".class": "UnionType", "items": ["builtins.str", {".class": "NoneType"}]}], "bound_args": [], "def_extras": {}, "fallback": "builtins.function", "implicit": false, "is_ellipsis_args": false, "name": "__init__ of Entity", "ret_type": {".class": "NoneType"}, "variables": []}}, "plugin_generated": true}, "end": {".class": "SymbolTableNode", "implicit": true, "kind": "Mdef", "node": {".class": "Var", "flags": ["is_initialized_in_class", "is_ready"], "fullname": "pybrat.parser.Entity.end", "name": "end", "type": "builtins.int"}}, "id": {".class": "SymbolTableNode", "kind": "Mdef", "node": {".class": "Var", "flags": ["is_initialized_in_class", "is_ready"], "fullname": "pybrat.parser.Entity.id", "name": "id", "type": {".class": "UnionType", "items": ["builtins.str", {".class": "NoneType"}]}}}, "mention": {".class": "SymbolTableNode", "implicit": true, "kind": "Mdef", "node": {".class": "Var", "flags": ["is_initialized_in_class", "is_ready"], "fullname": "pybrat.parser.Entity.mention", "name": "mention", "type": "builtins.str"}}, "references": {".class": "SymbolTableNode", "kind": "Mdef", "node": {".class": "Var", "flags": ["is_initialized_in_class", "is_ready"], "fullname": "pybrat.parser.Entity.references", "name": "references", "type": {".class": "Instance", "args": ["pybrat.parser.Reference"], "type_ref": "builtins.list"}}}, "start": {".class": "SymbolTableNode", "implicit": true, "kind": "Mdef", "node": {".class": "Var", "flags": ["is_initialized_in_class", "is_ready"], "fullname": "pybrat.parser.Entity.start", "name": "start", "type": "builtins.int"}}, "type": {".class": "SymbolTableNode", "implicit": true, "kind": "Mdef", "node": {".class": "Var", "flags": ["is_initialized_in_class", "is_ready"], "fullname": "pybrat.parser.Entity.type", "name": "type", "type": "builtins.str"}}}, "tuple_type": null, "type_vars": [], "typeddict_type": null}}, "Event": {".class": "SymbolTableNode", "kind": "Gdef", "node": {".class": "TypeInfo", "_promote": null, "abstract_attributes": [], "bases": ["builtins.object"], "declared_metaclass": null, "defn": {".class": "ClassDef", "fullname": "pybrat.parser.Event", "name": "Event", "type_vars": []}, "flags": [], "fullname": "pybrat.parser.Event", "metaclass_type": null, "metadata": {"dataclass": {"attributes": [{"column": 4, "has_default": false, "is_in_init": true, "is_init_var": false, "line": 49, "name": "type", "type": "builtins.str"}, {"column": 4, "has_default": false, "is_in_init": true, "is_init_var": false, "line": 50, "name": "trigger", "type": "pybrat.parser.Entity"}, {"column": 4, "has_default": true, "is_in_init": true, "is_init_var": false, "line": 51, "name": "arguments", "type": {".class": "Instance", "args": ["pybrat.parser.Event.Argument"], "type_ref": "builtins.list"}}, {"column": 4, "has_default": true, "is_in_init": true, "is_init_var": false, "line": 52, "name": "id", "type": {".class": "UnionType", "items": ["builtins.str", {".class": "NoneType"}]}}], "frozen": false}}, "module_name": "pybrat.parser", "mro": ["pybrat.parser.Event", "builtins.object"], "names": {".class": "SymbolTable", "Argument": {".class": "SymbolTableNode", "kind": "Mdef", "node": {".class": "TypeInfo", "_promote": null, "abstract_attributes": [], "bases": ["builtins.object"], "declared_metaclass": null, "defn": {".class": "ClassDef", "fullname": "pybrat.parser.Event.Argument", "name": "Argument", "type_vars": []}, "flags": [], "fullname": "pybrat.parser.Event.Argument", "metaclass_type": null, "metadata": {"dataclass": {"attributes": [{"column": 8, "has_default": false, "is_in_init": true, "is_init_var": false, "line": 46, "name": "rule", "type": "builtins.str"}, {"column": 8, "has_default": false, "is_in_init": true, "is_init_var": false, "line": 47, "name": "entity", "type": "pybrat.parser.Entity"}], "frozen": false}}, "module_name": "pybrat.parser", "mro": ["pybrat.parser.Event.Argument", "builtins.object"], "names": {".class": "SymbolTable", "__init__": {".class": "SymbolTableNode", "kind": "Mdef", "node": {".class": "FuncDef", "arg_kinds": [0, 0, 0], "arg_names": ["self", "rule", "entity"], "flags": [], "fullname": "pybrat.parser.Event.Argument.__init__", "name": "__init__", "type": {".class": "CallableType", "arg_kinds": [0, 0, 0], "arg_names": ["self", "rule", "entity"], "arg_types": ["pybrat.parser.Event.Argument", "builtins.str", "pybrat.parser.Entity"], "bound_args": [], "def_extras": {}, "fallback": "builtins.function", "implicit": false, "is_ellipsis_args": false, "name": "__init__ of Argument", "ret_type": {".class": "NoneType"}, "variables": []}}, "plugin_generated": true}, "entity": {".class": "SymbolTableNode", "implicit": true, "kind": "Mdef", "node": {".class": "Var", "flags": ["is_initialized_in_class", "is_ready"], "fullname": "pybrat.parser.Event.Argument.entity", "name": "entity", "type": "pybrat.parser.Entity"}}, "rule": {".class": "SymbolTableNode", "implicit": true, "kind": "Mdef", "node": {".class": "Var", "flags": ["is_initialized_in_class", "is_ready"], "fullname": "pybrat.parser.Event.Argument.rule", "name": "rule", "type": "builtins.str"}}}, "tuple_type": null, "type_vars": [], "typeddict_type": null}}, "__init__": {".class": "SymbolTableNode", "kind": "Mdef", "node": {".class": "FuncDef", "arg_kinds": [0, 0, 0, 1, 1], "arg_names": ["self", "type", "trigger", "arguments", "id"], "flags": [], "fullname": "pybrat.parser.Event.__init__", "name": "__init__", "type": {".class": "CallableType", "arg_kinds": [0, 0, 0, 1, 1], "arg_names": ["self", "type", "trigger", "arguments", "id"], "arg_types": ["pybrat.parser.Event", "builtins.str", "pybrat.parser.Entity", {".class": "Instance", "args": ["pybrat.parser.Event.Argument"], "type_ref": "builtins.list"}, {".class": "UnionType", "items": ["builtins.str", {".class": "NoneType"}]}], "bound_args": [], "def_extras": {}, "fallback": "builtins.function", "implicit": false, "is_ellipsis_args": false, "name": "__init__ of Event", "ret_type": {".class": "NoneType"}, "variables": []}}, "plugin_generated": true}, "arguments": {".class": "SymbolTableNode", "kind": "Mdef", "node": {".class": "Var", "flags": ["is_initialized_in_class", "is_ready"], "fullname": "pybrat.parser.Event.arguments", "name": "arguments", "type": {".class": "Instance", "args": ["pybrat.parser.Event.Argument"], "type_ref": "builtins.list"}}}, "id": {".class": "SymbolTableNode", "kind": "Mdef", "node": {".class": "Var", "flags": ["is_initialized_in_class", "is_ready"], "fullname": "pybrat.parser.Event.id", "name": "id", "type": {".class": "UnionType", "items": ["builtins.str", {".class": "NoneType"}]}}}, "trigger": {".class": "SymbolTableNode", "implicit": true, "kind": "Mdef", "node": {".class": "Var", "flags": ["is_initialized_in_class", "is_ready"], "fullname": "pybrat.parser.Event.trigger", "name": "trigger", "type": "pybrat.parser.Entity"}}, "type": {".class": "SymbolTableNode", "implicit": true, "kind": "Mdef", "node": {".class": "Var", "flags": ["is_initialized_in_class", "is_ready"], "fullname": "pybrat.parser.Event.type", "name": "type", "type": "builtins.str"}}}, "tuple_type": null, "type_vars": [], "typeddict_type": null}}, "Example": {".class": "SymbolTableNode", "kind": "Gdef", "node": {".class": "TypeInfo", "_promote": null, "abstract_attributes": [], "bases": ["builtins.object"], "declared_metaclass": null, "defn": {".class": "ClassDef", "fullname": "pybrat.parser.Example", "name": "Example", "type_vars": []}, "flags": [], "fullname": "pybrat.parser.Example", "metaclass_type": null, "metadata": {"dataclass": {"attributes": [{"column": 4, "has_default": false, "is_in_init": true, "is_init_var": false, "line": 57, "name": "text", "type": {".class": "UnionType", "items": ["builtins.str", {".class": "Instance", "args": ["builtins.str"], "type_ref": "typing.Iterable"}]}}, {"column": 4, "has_default": true, "is_in_init": true, "is_init_var": false, "line": 58, "name": "entities", "type": {".class": "Instance", "args": ["pybrat.parser.Entity"], "type_ref": "builtins.list"}}, {"column": 4, "has_default": true, "is_in_init": true, "is_init_var": false, "line": 59, "name": "relations", "type": {".class": "Instance", "args": ["pybrat.parser.Relation"], "type_ref": "builtins.list"}}, {"column": 4, "has_default": true, "is_in_init": true, "is_init_var": false, "line": 60, "name": "events", "type": {".class": "Instance", "args": ["pybrat.parser.Event"], "type_ref": "builtins.list"}}, {"column": 4, "has_default": true, "is_in_init": true, "is_init_var": false, "line": 61, "name": "id", "type": {".class": "UnionType", "items": ["builtins.str", {".class": "NoneType"}]}}], "frozen": false}}, "module_name": "pybrat.parser", "mro": ["pybrat.parser.Example", "builtins.object"], "names": {".class": "SymbolTable", "__init__": {".class": "SymbolTableNode", "kind": "Mdef", "node": {".class": "FuncDef", "arg_kinds": [0, 0, 1, 1, 1, 1], "arg_names": ["self", "text", "entities", "relations", "events", "id"], "flags": [], "fullname": "pybrat.parser.Example.__init__", "name": "__init__", "type": {".class": "CallableType", "arg_kinds": [0, 0, 1, 1, 1, 1], "arg_names": ["self", "text", "entities", "relations", "events", "id"], "arg_types": ["pybrat.parser.Example", {".class": "UnionType", "items": ["builtins.str", {".class": "Instance", "args": ["builtins.str"], "type_ref": "typing.Iterable"}]}, {".class": "Instance", "args": ["pybrat.parser.Entity"], "type_ref": "builtins.list"}, {".class": "Instance", "args": ["pybrat.parser.Relation"], "type_ref": "builtins.list"}, {".class": "Instance", "args": ["pybrat.parser.Event"], "type_ref": "builtins.list"}, {".class": "UnionType", "items": ["builtins.str", {".class": "NoneType"}]}], "bound_args": [], "def_extras": {}, "fallback": "builtins.function", "implicit": false, "is_ellipsis_args": false, "name": "__init__ of Example", "ret_type": {".class": "NoneType"}, "variables": []}}, "plugin_generated": true}, "entities": {".class": "SymbolTableNode", "kind": "Mdef", "node": {".class": "Var", "flags": ["is_initialized_in_class", "is_ready"], "fullname": "pybrat.parser.Example.entities", "name": "entities", "type": {".class": "Instance", "args": ["pybrat.parser.Entity"], "type_ref": "builtins.list"}}}, "events": {".class": "SymbolTableNode", "kind": "Mdef", "node": {".class": "Var", "flags": ["is_initialized_in_class", "is_ready"], "fullname": "pybrat.parser.Example.events", "name": "events", "type": {".class": "Instance", "args": ["pybrat.parser.Event"], "type_ref": "builtins.list"}}}, "id": {".class": "SymbolTableNode", "kind": "Mdef", "node": {".class": "Var", "flags": ["is_initialized_in_class", "is_ready"], "fullname": "pybrat.parser.Example.id", "name": "id", "type": {".class": "UnionType", "items": ["builtins.str", {".class": "NoneType"}]}}}, "relations": {".class": "SymbolTableNode", "kind": "Mdef", "node": {".class": "Var", "flags": ["is_initialized_in_class", "is_ready"], "fullname": "pybrat.parser.Example.relations", "name": "relations", "type": {".class": "Instance", "args": ["pybrat.parser.Relation"], "type_ref": "builtins.list"}}}, "text": {".class": "SymbolTableNode", "implicit": true, "kind": "Mdef", "node": {".class": "Var", "flags": ["is_initialized_in_class", "is_ready"], "fullname": "pybrat.parser.Example.text", "name": "text", "type": {".class": "UnionType", "items": ["builtins.str", {".class": "Instance", "args": ["builtins.str"], "type_ref": "typing.Iterable"}]}}}}, "tuple_type": null, "type_vars": [], "typeddict_type": null}}, "Iterable": {".class": "SymbolTableNode", "cross_ref": "typing.Iterable", "kind": "Gdef"}, "Optional": {".class": "SymbolTableNode", "cross_ref": "typing.Optional", "kind": "Gdef"}, "Reference": {".class": "SymbolTableNode", "kind": "Gdef", "node": {".class": "TypeInfo", "_promote": null, "abstract_attributes": [], "bases": ["builtins.object"], "declared_metaclass": null, "defn": {".class": "ClassDef", "fullname": "pybrat.parser.Reference", "name": "Reference", "type_vars": []}, "flags": [], "fullname": "pybrat.parser.Reference", "metaclass_type": null, "metadata": {"dataclass": {"attributes": [{"column": 4, "has_default": false, "is_in_init": true, "is_init_var": false, "line": 18, "name": "rid", "type": "builtins.str"}, {"column": 4, "has_default": false, "is_in_init": true, "is_init_var": false, "line": 19, "name": "eid", "type": "builtins.str"}, {"column": 4, "has_default": false, "is_in_init": true, "is_init_var": false, "line": 20, "name": "entry", "type": "builtins.str"}, {"column": 4, "has_default": true, "is_in_init": true, "is_init_var": false, "line": 21, "name": "id", "type": {".class": "UnionType", "items": ["builtins.str", {".class": "NoneType"}]}}], "frozen": false}}, "module_name": "pybrat.parser", "mro": ["pybrat.parser.Reference", "builtins.object"], "names": {".class": "SymbolTable", "__init__": {".class": "SymbolTableNode", "kind": "Mdef", "node": {".class": "FuncDef", "arg_kinds": [0, 0, 0, 0, 1], "arg_names": ["self", "rid", "eid", "entry", "id"], "flags": [], "fullname": "pybrat.parser.Reference.__init__", "name": "__init__", "type": {".class": "CallableType", "arg_kinds": [0, 0, 0, 0, 1], "arg_names": ["self", "rid", "eid", "entry", "id"], "arg_types": ["pybrat.parser.Reference", "builtins.str", "builtins.str", "builtins.str", {".class": "UnionType", "items": ["builtins.str", {".class": "NoneType"}]}], "bound_args": [], "def_extras": {}, "fallback": "builtins.function", "implicit": false, "is_ellipsis_args": false, "name": "__init__ of Reference", "ret_type": {".class": "NoneType"}, "variables": []}}, "plugin_generated": true}, "eid": {".class": "SymbolTableNode", "implicit": true, "kind": "Mdef", "node": {".class": "Var", "flags": ["is_initialized_in_class", "is_ready"], "fullname": "pybrat.parser.Reference.eid", "name": "eid", "type": "builtins.str"}}, "entry": {".class": "SymbolTableNode", "implicit": true, "kind": "Mdef", "node": {".class": "Var", "flags": ["is_initialized_in_class", "is_ready"], "fullname": "pybrat.parser.Reference.entry", "name": "entry", "type": "builtins.str"}}, "id": {".class": "SymbolTableNode", "kind": "Mdef", "node": {".class": "Var", "flags": ["is_initialized_in_class", "is_ready"], "fullname": "pybrat.parser.Reference.id", "name": "id", "type": {".class": "UnionType", "items": ["builtins.str", {".class": "NoneType"}]}}}, "rid": {".class": "SymbolTableNode", "implicit": true, "kind": "Mdef", "node": {".class": "Var", "flags": ["is_initialized_in_class", "is_ready"], "fullname": "pybrat.parser.Reference.rid", "name": "rid", "type": "builtins.str"}}}, "tuple_type": null, "type_vars": [], "typeddict_type": null}}, "Relation": {".class": "SymbolTableNode", "kind": "Gdef", "node": {".class": "TypeInfo", "_promote": null, "abstract_attributes": [], "bases": ["builtins.object"], "declared_metaclass": null, "defn": {".class": "ClassDef", "fullname": "pybrat.parser.Relation", "name": "Relation", "type_vars": []}, "flags": [], "fullname": "pybrat.parser.Relation", "metaclass_type": null, "metadata": {"dataclass": {"attributes": [{"column": 4, "has_default": false, "is_in_init": true, "is_init_var": false, "line": 36, "name": "type", "type": "builtins.str"}, {"column": 4, "has_default": false, "is_in_init": true, "is_init_var": false, "line": 37, "name": "arg1", "type": "pybrat.parser.Entity"}, {"column": 4, "has_default": false, "is_in_init": true, "is_init_var": false, "line": 38, "name": "arg2", "type": "pybrat.parser.Entity"}, {"column": 4, "has_default": true, "is_in_init": true, "is_init_var": false, "line": 39, "name": "id", "type": {".class": "UnionType", "items": ["builtins.str", {".class": "NoneType"}]}}], "frozen": false}}, "module_name": "pybrat.parser", "mro": ["pybrat.parser.Relation", "builtins.object"], "names": {".class": "SymbolTable", "__init__": {".class": "SymbolTableNode", "kind": "Mdef", "node": {".class": "FuncDef", "arg_kinds": [0, 0, 0, 0, 1], "arg_names": ["self", "type", "arg1", "arg2", "id"], "flags": [], "fullname": "pybrat.parser.Relation.__init__", "name": "__init__", "type": {".class": "CallableType", "arg_kinds": [0, 0, 0, 0, 1], "arg_names": ["self", "type", "arg1", "arg2", "id"], "arg_types": ["pybrat.parser.Relation", "builtins.str", "pybrat.parser.Entity", "pybrat.parser.Entity", {".class": "UnionType", "items": ["builtins.str", {".class": "NoneType"}]}], "bound_args": [], "def_extras": {}, "fallback": "builtins.function", "implicit": false, "is_ellipsis_args": false, "name": "__init__ of Relation", "ret_type": {".class": "NoneType"}, "variables": []}}, "plugin_generated": true}, "arg1": {".class": "SymbolTableNode", "implicit": true, "kind": "Mdef", "node": {".class": "Var", "flags": ["is_initialized_in_class", "is_ready"], "fullname": "pybrat.parser.Relation.arg1", "name": "arg1", "type": "pybrat.parser.Entity"}}, "arg2": {".class": "SymbolTableNode", "implicit": true, "kind": "Mdef", "node": {".class": "Var", "flags": ["is_initialized_in_class", "is_ready"], "fullname": "pybrat.parser.Relation.arg2", "name": "arg2", "type": "pybrat.parser.Entity"}}, "id": {".class": "SymbolTableNode", "kind": "Mdef", "node": {".class": "Var", "flags": ["is_initialized_in_class", "is_ready"], "fullname": "pybrat.parser.Relation.id", "name": "id", "type": {".class": "UnionType", "items": ["builtins.str", {".class": "NoneType"}]}}}, "type": {".class": "SymbolTableNode", "implicit": true, "kind": "Mdef", "node": {".class": "Var", "flags": ["is_initialized_in_class", "is_ready"], "fullname": "pybrat.parser.Relation.type", "name": "type", "type": "builtins.str"}}}, "tuple_type": null, "type_vars": [], "typeddict_type": null}}, "Union": {".class": "SymbolTableNode", "cross_ref": "typing.Union", "kind": "Gdef"}, "__doc__": {".class": "SymbolTableNode", "kind": "Gdef", "node": {".class": "Var", "flags": ["is_ready"], "fullname": "pybrat.parser.__doc__", "name": "__doc__", "type": "builtins.str"}}, "__file__": {".class": "SymbolTableNode", "kind": "Gdef", "node": {".class": "Var", "flags": ["is_ready"], "fullname": "pybrat.parser.__file__", "name": "__file__", "type": "builtins.str"}}, "__name__": {".class": "SymbolTableNode", "kind": "Gdef", "node": {".class": "Var", "flags": ["is_ready"], "fullname": "pybrat.parser.__name__", "name": "__name__", "type": "builtins.str"}}, "__package__": {".class": "SymbolTableNode", "kind": "Gdef", "node": {".class": "Var", "flags": ["is_ready"], "fullname": "pybrat.parser.__package__", "name": "__package__", "type": "builtins.str"}}, "annotations": {".class": "SymbolTableNode", "cross_ref": "__future__.annotations", "kind": "Gdef"}, "collections": {".class": "SymbolTableNode", "cross_ref": "collections", "kind": "Gdef"}, "dataclasses": {".class": "SymbolTableNode", "cross_ref": "dataclasses", "kind": "Gdef"}, "iter_file_groups": {".class": "SymbolTableNode", "cross_ref": "pybrat.utils.iter_file_groups", "kind": "Gdef"}, "itertools": {".class": "SymbolTableNode", "cross_ref": "itertools", "kind": "Gdef"}, "os": {".class": "SymbolTableNode", "cross_ref": "os", "kind": "Gdef"}, "re": {".class": "SymbolTableNode", "cross_ref": "re", "kind": "Gdef"}}, "path": "/Users/Maximin/git/pybrat/pybrat/parser.py"}